{
	"credit": "Made with Blockbench",
	"ambientocclusion": false,
	"textures": {
		"1": "block/warped_fungus/stem",
		"2": "block/warped_fungus/warped_fungus_1",
		"3": "block/warped_fungus/warped_fungus_2",
		"particle": "block/warped_fungus/warped_fungus_2"
	},
	"elements": [
		{
			"from": [5.54147, -0.9, 10.87104],
			"to": [6.92147, 1.6875, 12.25104],
			"rotation": {"angle": -22.5, "axis": "y", "origin": [6.23147, 3.02437, 11.56104]},
			"faces": {
				"north": {"uv": [0, 12.25, 2, 16], "texture": "#1"},
				"east": {"uv": [0, 12.25, 2, 16], "texture": "#1"},
				"south": {"uv": [0, 12.25, 2, 16], "texture": "#1"},
				"west": {"uv": [0, 12.25, 2, 16], "texture": "#1"},
				"down": {"uv": [11.5, 11.5, 13.5, 13.5], "texture": "#1"}
			}
		},
		{
			"from": [5.19647, 1.6875, 10.52604],
			"to": [7.26647, 3.585, 12.59604],
			"rotation": {"angle": -22.5, "axis": "y", "origin": [6.23147, 3.02437, 11.56104]},
			"faces": {
				"north": {"uv": [0, 8.1875, 3, 10.9375], "texture": "#1"},
				"east": {"uv": [0, 8.1875, 3, 10.9375], "texture": "#1"},
				"south": {"uv": [0, 8.1875, 3, 10.9375], "texture": "#1"},
				"west": {"uv": [0, 8.1875, 3, 10.9375], "texture": "#1"},
				"down": {"uv": [11, 11, 14, 14], "texture": "#1"}
			}
		},
		{
			"from": [10.45069, -1.9, 4.11405],
			"to": [11.83069, 0.6875, 5.49405],
			"rotation": {"angle": 22.5, "axis": "y", "origin": [11.14069, 2.02438, 4.80405]},
			"faces": {
				"north": {"uv": [0, 12.25, 2, 16], "texture": "#1"},
				"east": {"uv": [0, 12.25, 2, 16], "texture": "#1"},
				"south": {"uv": [0, 12.25, 2, 16], "texture": "#1"},
				"west": {"uv": [0, 12.25, 2, 16], "texture": "#1"},
				"down": {"uv": [11.5, 11.5, 13.5, 13.5], "texture": "#1"}
			}
		},
		{
			"from": [10.10569, 0.6875, 3.76905],
			"to": [12.17569, 2.585, 5.83905],
			"rotation": {"angle": 22.5, "axis": "y", "origin": [11.14069, 2.02438, 4.80405]},
			"faces": {
				"north": {"uv": [0, 8.1875, 3, 10.9375], "texture": "#1"},
				"east": {"uv": [0, 8.1875, 3, 10.9375], "texture": "#1"},
				"south": {"uv": [0, 8.1875, 3, 10.9375], "texture": "#1"},
				"west": {"uv": [0, 8.1875, 3, 10.9375], "texture": "#1"},
				"down": {"uv": [11, 11, 14, 14], "texture": "#1"}
			}
		},
		{
			"from": [-1.8, 4.035, 3.6],
			"to": [14.2, 4.035, 19.6],
			"rotation": {"angle": -45, "axis": "y", "origin": [6.2, 4.035, 11.6]},
			"faces": {
				"up": {"uv": [0, 0, 16, 16], "rotation": 90, "texture": "#2"}
			}
		},
		{
			"from": [3.2, 2.935, -3.4],
			"to": [19.2, 2.935, 12.6],
			"rotation": {"angle": -45, "axis": "y", "origin": [11.2, 2.935, 4.6]},
			"faces": {
				"up": {"uv": [0, 0, 16, 16], "rotation": 90, "texture": "#3"}
			}
		}
	],
	"groups": [
		{
			"name": "group",
			"origin": [2.48, 0, 2.48],
			"color": 0,
			"children": [0, 1]
		},
		{
			"name": "group",
			"origin": [2.48, 0, 2.48],
			"color": 0,
			"children": [2, 3]
		},
		{
			"name": "group",
			"origin": [2.48, 0, 2.48],
			"color": 0,
			"children": []
		},
		4,
		5
	]
}